COPYING
MANIFEST.in
setup.py
bin/pyeval
lib/pyeval/__init__.py
lib/pyeval/autoimporter.py
lib/pyeval/copyright.py
lib/pyeval/display.py
lib/pyeval/eval.py
lib/pyeval/help.py
lib/pyeval/indentation.py
lib/pyeval/main.py
lib/pyeval/monkeypatch.py
lib/pyeval.egg-info/PKG-INFO
lib/pyeval.egg-info/SOURCES.txt
lib/pyeval.egg-info/dependency_links.txt
lib/pyeval.egg-info/top_level.txt
lib/pyeval/doc/AutoImporter.txt
lib/pyeval/doc/encoding.txt
lib/pyeval/doc/examples.txt
lib/pyeval/doc/help.txt
lib/pyeval/doc/intro.txt
lib/pyeval/doc/magic.txt
lib/pyeval/doc/upgrading.txt
lib/pyeval/magic/__init__.py
lib/pyeval/magic/functions.py
lib/pyeval/magic/scope.py
lib/pyeval/magic/variables.py
lib/pyeval/tests/__init__.py
lib/pyeval/tests/fakeio.py
lib/pyeval/tests/test_autoimporter.py
lib/pyeval/tests/test_display.py
lib/pyeval/tests/test_eval.py
lib/pyeval/tests/test_help.py
lib/pyeval/tests/test_indentation.py
lib/pyeval/tests/test_magicscope.py
lib/pyeval/tests/test_main.py