Metadata-Version: 1.0
Name: pyeval
Version: 0.2
Summary: Conveniently evaluate expressions from the shell
Home-page: https://bitbucket.org/nejucomo/pyeval
Author: Nathan Wilcox
Author-email: nejucomo@gmail.com
License: GPLv3
Platform: UNKNOWN
